{
	"name": "dataflow2",
	"properties": {
		"type": "MappingDataFlow",
		"typeProperties": {
			"sources": [
				{
					"dataset": {
						"referenceName": "payroll",
						"type": "DatasetReference"
					},
					"name": "source1"
				}
			],
			"sinks": [
				{
					"dataset": {
						"referenceName": "PayrollFilter",
						"type": "DatasetReference"
					},
					"name": "sink1"
				}
			],
			"transformations": [
				{
					"name": "filter1"
				}
			],
			"scriptLines": [
				"source(output(",
				"          PAYROLL_NAME as string,",
				"          DAY as string",
				"     ),",
				"     allowSchemaDrift: true,",
				"     validateSchema: false,",
				"     ignoreNoFilesFound: false,",
				"     partitionBy('hash', 1)) ~> source1",
				"source1 filter(DAY=='16') ~> filter1",
				"filter1 sink(allowSchemaDrift: true,",
				"     validateSchema: false,",
				"     input(",
				"          PAYROLL_NAME as string,",
				"          DAY as string",
				"     ),",
				"     partitionFileNames:['Filter'],",
				"     skipDuplicateMapInputs: true,",
				"     skipDuplicateMapOutputs: true,",
				"     saveOrder: 1,",
				"     mapColumn(",
				"          PAYROLL_NAME",
				"     ),",
				"     partitionBy('hash', 1)) ~> sink1"
			]
		}
	}
}